README.rst
setup.py
spliterator/__init__.py
spliterator.egg-info/PKG-INFO
spliterator.egg-info/SOURCES.txt
spliterator.egg-info/dependency_links.txt
spliterator.egg-info/top_level.txt